[
  {
    "slug": "Men-Briefs",
    "name": "Esteem Men Cotton Briefs (Combo Pack of 5)",
    "images": [
      "https://res.cloudinary.com/desmywzoz/image/upload/v1776949185/men-brief_rhvljg.avif"
    ],
    "sizeChart": "https://res.cloudinary.com/desmywzoz/image/upload/v1776949538/size-chart-men-brief_zxufiv.jpg",
    "sizes": [
      {
        "size": "85 cm",
        "price": 299
      },
      {
        "size": "90 cm",
        "price": 320
      },
      {
        "size": "95 cm",
        "price": 325
      },
      {
        "size": "100 cm",
        "price": 330
      },
      {
        "size": "105 cm",
        "price": 335
      },
      {
        "size": "110 cm",
        "price": 340
      }
    ],
    "links": [
      {
        "seller": "Esteem Innerwears",
        "platform": "amazon",
        "url": "https://www.amazon.in/Esteem-Elastic-Underwear-Numeric-Multicolor/dp/B0F53J74FN",
        "rating": 4.1
      },
      {
        "seller": "KeyarExports",
        "platform": "flipkart",
        "url": "https://www.flipkart.com/esteem-men-brief/p/itm6694cad5842b4",
        "rating": 4.2
      },
      {
        "platform": "meesho",
        "seller": "KEYAR EXPORTS",
        "url": "https://www.meesho.com/esteem-mens-solid-cotton-briefs-combo-pack-of-5/p/7m2yn9",
        "rating": 4.3
      }
    ],
    "details": [
      "100% Cotton Fabric",
      "Breathable & Sweat Absorbent",
      "Soft Elastic Waistband",
      "Durable Stitching",
      "Assorted colors combo pack of 5"
    ]
  },
  {
    "slug": "Men-Briefs",
    "name": "Esteem Men Cotton Briefs (Combo Pack of 5)",
    "images": [
      "https://res.cloudinary.com/desmywzoz/image/upload/v1777279445/ks1fk_512_yrtbjh.avif"
    ],
    "sizeChart": "https://res.cloudinary.com/desmywzoz/image/upload/v1776949538/size-chart-men-brief_zxufiv.jpg",
    "sizes": [
      {
        "size": "85 cm",
        "price": 299
      },
      {
        "size": "90 cm",
        "price": 299
      },
      {
        "size": "95 cm",
        "price": 299
      },
      {
        "size": "100 cm",
        "price": 299
      },
      {
        "size": "105 cm",
        "price": 299
      },
      {
        "size": "110 cm",
        "price": 299
      }
    ],
    "links": [
      {
        "seller": "Esteem Innerwears",
        "platform": "amazon",
        "url": "https://www.amazon.in/EstEEm-Mens-Innerwear-Garment-Multicolour/dp/B0CTWPLVBY",
        "rating": 3.8
      },
      {
        "seller": "KeyarExports",
        "platform": "flipkart",
        "url": "https://www.flipkart.com/esteem-men-brief/p/itm0a4b6edbff98e",
        "rating": 3.9
      },
      {
        "platform": "meesho",
        "seller": "KEYAR EXPORTS",
        "url": "https://www.meesho.com/esteem-mens-solid-cotton-briefs-combo-pack-of-5/p/u1ljl",
        "rating": 4.0
      }
    ],
    "details": [
      "100% Cotton Fabric",
      "Breathable & Sweat Absorbent",
      "Soft Elastic Waistband",
      "Durable Stitching",
      "Assorted colors combo pack of 5"
    ]
  },
  {
    "slug": "esteem-mens-cotton-rib-gym-vestpack-of-3",
    "name": "Esteem Mens Cotton Rib Gym Vest(Pack of 3)",
    "images": [
      "https://res.cloudinary.com/desmywzoz/image/upload/v1777278330/gym--vest-1_r5sent.webp"
    ],
    "sizeChart": "https://res.cloudinary.com/desmywzoz/image/upload/v1777278507/Screenshot_2026-04-27_135813_gbutni.png",
    "sizes": [
      {
        "size": "M",
        "price": 382
      },
      {
        "size": "L",
        "price": 383
      },
      {
        "size": "XL",
        "price": 383
      },
      {
        "size": "XXl",
        "price": 383
      }
    ],
    "links": [
      {
        "platform": "meesho",
        "seller": "KEYAR EXPORTS",
        "url": "https://www.meesho.com/esteem-mens-cotton-rib-gym-vestpack-of-3/p/4ox9ag",
        "rating": 4.1
      },
      {
        "platform": "flipkart",
        "seller": "KeyarExports",
        "url": "https://www.flipkart.com/esteem-men-vest/p/itmbc655bd4e3f89",
        "rating": 4.1
      }
    ],
    "details": [
      "100% cotton",
      "Knitted Combed Rib Cloth",
      "Pack Of 3 Bright Primary Colors"
    ]
  },
  {
    "slug": "esteem-mens-cotton-RIB-gym-vestpack-of-3",
    "name": "Esteem Mens Cotton RIB Gym Vest (Pack of 3)",
    "images": [
      "https://res.cloudinary.com/desmywzoz/image/upload/v1777279280/gym--vest-2_gmaea9.avif"
    ],
    "sizeChart": "https://res.cloudinary.com/desmywzoz/image/upload/v1777278507/Screenshot_2026-04-27_135813_gbutni.png",
    "sizes": [
      {
        "size": "M",
        "price": 382
      },
      {
        "size": "L",
        "price": 383
      },
      {
        "size": "XL",
        "price": 383
      },
      {
        "size": "XXl",
        "price": 383
      }
    ],
    "links": [
      {
        "platform": "meesho",
        "seller": "KEYAR EXPORTS",
        "url": "https://www.meesho.com/esteem-mens-cotton-rib-gym-vest-pack-of-3/p/p5ew7",
        "rating": 4.1
      },
      {
        "platform": "flipkart",
        "seller": "KeyarExports",
        "url": "https://www.flipkart.com/esteem-men-vest/p/itmd44a06bd2dd34",
        "rating": 4.0
      }
    ],
    "details": [
      "100% cotton",
      "Knitted Combed Rib Cloth",
      "Pack Of 3 Bright Primary Colors"
    ]
  }
]
